rfkit/__init__.py
rfkit/io/__init__.py
rfkit/io/io.py
rfkit/math/__init__.py
rfkit/math/math.py
pyrfkit-1.1.0.dist-info/LICENSE.md
pyrfkit-1.1.0.dist-info/WHEEL
pyrfkit-1.1.0.dist-info/METADATA
pyrfkit-1.1.0.dist-info/RECORD
